README.md
setup.py
hoverboots/__init__.py
hoverboots/hoverboots.py
hoverboots.egg-info/PKG-INFO
hoverboots.egg-info/SOURCES.txt
hoverboots.egg-info/dependency_links.txt
hoverboots.egg-info/entry_points.txt
hoverboots.egg-info/top_level.txt