Metadata-Version: 1.1
Name: hoverboots
Version: 0.0.1
Summary: hoverboots
Home-page: https://github.com/vesche/hoverboots
Author: Austin Jackson
Author-email: vesche@protonmail.com
License: MIT
Platform: UNKNOWN
Classifier: Development Status :: 1 - Planning
Classifier: License :: OSI Approved :: MIT License
Classifier: Programming Language :: Python :: 3
